LICENSE
MANIFEST.in
NOTICE
README.md
requirements.txt
setup.cfg
setup.py
compiler/__init__.py
compiler/api/__init__.py
compiler/api/compiler.py
compiler/api/source/auth_key.tl
compiler/api/source/main_api.tl
compiler/api/source/sys_msgs.tl
compiler/api/template/combinator.txt
compiler/api/template/type.txt
compiler/errors/__init__.py
compiler/errors/compiler.py
compiler/errors/sort.py
compiler/errors/source/303_SEE_OTHER.tsv
compiler/errors/source/400_BAD_REQUEST.tsv
compiler/errors/source/401_UNAUTHORIZED.tsv
compiler/errors/source/403_FORBIDDEN.tsv
compiler/errors/source/406_NOT_ACCEPTABLE.tsv
compiler/errors/source/420_FLOOD.tsv
compiler/errors/source/500_INTERNAL_SERVER_ERROR.tsv
compiler/errors/source/503_SERVICE_UNAVAILABLE.tsv
compiler/errors/template/class.txt
compiler/errors/template/sub_class.txt
orangtua/__init__.py
orangtua/client.py
orangtua/dispatcher.py
orangtua/emoji.py
orangtua/file_id.py
orangtua/filters.py
orangtua/mime_types.py
orangtua/py.typed
orangtua/sync.py
orangtua/utils.py
orangtua.egg-info/PKG-INFO
orangtua.egg-info/SOURCES.txt
orangtua.egg-info/dependency_links.txt
orangtua.egg-info/not-zip-safe
orangtua.egg-info/requires.txt
orangtua.egg-info/top_level.txt
orangtua/connection/__init__.py
orangtua/connection/connection.py
orangtua/connection/transport/__init__.py
orangtua/connection/transport/tcp/__init__.py
orangtua/connection/transport/tcp/tcp.py
orangtua/connection/transport/tcp/tcp_abridged.py
orangtua/connection/transport/tcp/tcp_abridged_o.py
orangtua/connection/transport/tcp/tcp_full.py
orangtua/connection/transport/tcp/tcp_intermediate.py
orangtua/connection/transport/tcp/tcp_intermediate_o.py
orangtua/crypto/__init__.py
orangtua/crypto/aes.py
orangtua/crypto/mtproto.py
orangtua/crypto/prime.py
orangtua/crypto/rsa.py
orangtua/enums/__init__.py
orangtua/enums/auto_name.py
orangtua/enums/chat_action.py
orangtua/enums/chat_event_action.py
orangtua/enums/chat_member_status.py
orangtua/enums/chat_members_filter.py
orangtua/enums/chat_type.py
orangtua/enums/message_entity_type.py
orangtua/enums/message_media_type.py
orangtua/enums/message_service_type.py
orangtua/enums/messages_filter.py
orangtua/enums/next_code_type.py
