Metadata-Version: 2.1
Name: orangtua
Version: 0.0.1
Summary: orangtua - Telegram MTProto API Client Library for Python.
Home-page: https://github.com/hitokizzy/orangtua
Author: hitokizzy
Author-email: hitokizzy@gmail.com
License: GNU Lesser General Public License v3.0 (LGPL-3.0)
Project-URL: Bug Tracker, https://github.com/hitokizzy/orangtua/issues
Project-URL: Documentation, https://orangtua.tech
Project-URL: Source Code, https://github.com/hitokizzy/orangtua
Platform: UNKNOWN
Classifier: Programming Language :: Python :: 3
Classifier: Programming Language :: Python :: 3.8
Classifier: Programming Language :: Python :: 3.9
Classifier: Programming Language :: Python :: 3.10
Classifier: License :: OSI Approved :: GNU General Public License v3 (GPLv3)
Classifier: Operating System :: OS Independent
Requires-Python: ~=3.7
License-File: LICENSE
License-File: NOTICE
